measureit/__init__.py
measureit/_deprecation.py
measureit/base_sweep.py
measureit/config.py
measureit/gate_leakage.py
measureit/logging_utils.py
measureit/simul_sweep.py
measureit/sweep0d.py
measureit/sweep1d.py
measureit/sweep1d_listening.py
measureit/sweep2d.py
measureit/sweep_ips.py
measureit/sweep_queue.py
measureit/tracking.py
measureit/util.py
measureit/Drivers/Ametek_7230.py
measureit/Drivers/BlueFors.py
measureit/Drivers/Dynacool.py
measureit/Drivers/HF2LI_xp.py
measureit/Drivers/ITC503.py
measureit/Drivers/Keithley_2450.py
measureit/Drivers/Keithley_2450_DW.py
measureit/Drivers/LM510.py
measureit/Drivers/LR.py
measureit/Drivers/Lakeshore_331.py
measureit/Drivers/M4G.py
measureit/Drivers/Model_340.py
measureit/Drivers/Model_372.py
measureit/Drivers/NDsweeper.py
measureit/Drivers/SCM10.py
measureit/Drivers/SR850.py
measureit/Drivers/SWbox3499.py
measureit/Drivers/VGC503.py
measureit/Drivers/__init__.py
measureit/Drivers/attodry.py
measureit/Drivers/cryocon_24.py
measureit/Drivers/daq_driver.py
measureit/Drivers/data/CyroCon24C_ChA_PID_Table_25Ohm.txt
measureit/Drivers/data/CyroCon24C_ChA_PID_Table_50Ohm.txt
measureit/Drivers/data/CyroCon24C_ChB_PID_Table.txt
measureit/_internal/__init__.py
measureit/_internal/plotter_thread.py
measureit/_internal/runner_thread.py
measureit/legacy/__init__.py
measureit/legacy/heatmap_thread_matplotlib.py
measureit/legacy/plotter_thread_matplotlib.py
measureit/sweep/__init__.py
measureit/sweep/base_sweep.py
measureit/sweep/gate_leakage.py
measureit/sweep/progress.py
measureit/sweep/simul_sweep.py
measureit/sweep/sweep0d.py
measureit/sweep/sweep1d.py
measureit/sweep/sweep1d_listening.py
measureit/sweep/sweep2d.py
measureit/sweep/sweep_ips.py
measureit/tools/__init__.py
measureit/tools/ipython.py
measureit/tools/safe_ramp.py
measureit/tools/sweep_queue.py
measureit/tools/tracking.py
measureit/tools/util.py
measureit/visualization/__init__.py
measureit/visualization/heatmap_thread.py
measureit/visualization/helper.py
qmeasure-1.2.6.dist-info/licenses/LICENSE
qmeasure-1.2.6.dist-info/METADATA
qmeasure-1.2.6.dist-info/WHEEL
qmeasure-1.2.6.dist-info/top_level.txt
qmeasure-1.2.6.dist-info/RECORD
